pyCoA/CoA.py
pyCoA/__init__.py
pycoa-0.0.4.dist-info/METADATA
pycoa-0.0.4.dist-info/WHEEL
pycoa-0.0.4.dist-info/licenses/LICENSE
pycoa-0.0.4.dist-info/RECORD
